bibfetch/__init__.py
bibfetch/__main__.py
bibfetch/dblp_fetcher.py
bibfetch/paper.py
bibfetch/semanticscholar_fetcher.py
bibfetch/utils.py
bibfetch-0.0.3.dist-info/METADATA
bibfetch-0.0.3.dist-info/WHEEL
bibfetch-0.0.3.dist-info/entry_points.txt
bibfetch-0.0.3.dist-info/top_level.txt
bibfetch-0.0.3.dist-info/RECORD
